<?xml version="1.0" encoding="utf-8" ?>
<dwsync>
<file name="generapdf.php" server="C:/xampp/htdocs/autorizacion/" local="131706161928225055" remote="131706161920000000" Dst="2" />
<file name="generapdf.php" server="C:/xampp/htdocs/autorizacion_ciclos_fpb/" local="131706161928225055" remote="131706161920000000" Dst="2" />
<file name="generapdf.php" server="C:/xampp/htdocs/datos_autorizacion_ciclos_fpb/" local="131709303364221947" remote="131709303360000000" Dst="2" />
<file name="generapdf.php" server="C:/xampp/htdocs/anulacion_matricula/" local="131715329325647700" remote="131715329320000000" Dst="2" />
<file name="generapdf.php" server="C:/xampp/htdocs/exencion_fct/" local="131720623576193000" remote="131720623570000000" Dst="2" />
<file name="generapdf.php" server="C:/xampp/htdocs/impresos_secretaria/exencion_fct/" local="131766439914175863" remote="131766439910000000" Dst="2" />
<file name="generapdf.php" server="C:/xampp/htdocs/impresos_secretaria/revision_calificacion/" local="132005656493119911" remote="132005656490000000" Dst="2" />
<file name="generapdf.php" server="C:/xampp/htdocs/impresos_secretaria/revision_examen/" local="132005735169730754" remote="132005735160000000" Dst="2" />
<file name="generapdf.php" server="C:/xampp/htdocs/impresos_secretaria/online/revision_examen/" local="132017734262856757" remote="132017734260000000" Dst="2" />
<file name="conexion.php" server="C:/xampp/htdocs/impresos_secretaria/online/revision_examen/" local="131970380217293111" remote="131970344210000000" Dst="2" />
<file name="conexion.php" server="D:/xampp/htdocs/impresos_secretaria/online/revision_examen/" local="132018229034004279" remote="132018229030000000" Dst="2" />
<file name="generapdf.php" server="D:/xampp/htdocs/impresos_secretaria/online/revision_examen/" local="132020365494002235" remote="132020365490000000" Dst="2" />
</dwsync>